Metadata-Version: 2.1
Name: visar
Version: 0.5.0
Summary: This project aims to train neural networks by compound-protein interactions and provides interpretation of the learned model by interactively showing transformed chemical landscape and visualized SAR for chemicals of interest.
Home-page: https://github.com/Svvord/visar
Author: Qingyang Ding
Author-email: dingqy14@mails.tsinghua.edu.cn
Maintainer: S. Hou
Maintainer-email: housy17@mails.tsinghua.edu.cn
License: MIT Licence
Keywords: Chemoinformatics,neural network,visualized structure-activity relationship,chemical landscape
Platform: any
